bulk_upload_testrail/__init__.py
bulk_upload_testrail/update_report.py
bulk_upload_testrail/upload_report.py
robot_framework_bulk_upload_testrail-0.0.2.dist-info/METADATA
robot_framework_bulk_upload_testrail-0.0.2.dist-info/WHEEL
robot_framework_bulk_upload_testrail-0.0.2.dist-info/top_level.txt
robot_framework_bulk_upload_testrail-0.0.2.dist-info/RECORD
