Metadata-Version: 2.1
Name: robot-framework-bulk-upload-testrail
Version: 0.0.2
Summary: A simple Python library for bulk upload to testrail in robot framework.
Author: Adi Darmawan
